qseispy/__init__.py
qseispy/gf/README.md
qseispy/gf/__init__.py
qseispy/gf/gf.py
qseispy/gf/note/image-1.png
qseispy/gf/note/image-2.png
qseispy/gf/note/image-3.png
qseispy/gf/note/image-4.png
qseispy/gf/note/image-5.png
qseispy/gf/note/image-6.png
qseispy/gf/note/image.png
qseispy/model/__init__.py
qseispy/model/config.py
qseispy/model/receiver.py
qseispy/model/source.py
qseispy/problem/__init__.py
qseispy/problem/problem.py
qseispy/solver/__init__.py
qseispy/solver/solver.py
qseispy/sync/__init__.py
qseispy/sync/sync.py
qseispy/taup/__init__.py
qseispy/taup/taup.py
qseispy/tests/__init__.py
qseispy/tests/data/2008_Mw_5.2_Carmel/IU_CCM.r
qseispy/tests/data/2008_Mw_5.2_Carmel/IU_CCM.t
qseispy/tests/data/2008_Mw_5.2_Carmel/IU_CCM.z
qseispy/tests/data/2008_Mw_5.2_Carmel/IU_WCI.r
qseispy/tests/data/2008_Mw_5.2_Carmel/IU_WCI.t
qseispy/tests/data/2008_Mw_5.2_Carmel/IU_WCI.z
qseispy/tests/data/2008_Mw_5.2_Carmel/IU_WVT.r
qseispy/tests/data/2008_Mw_5.2_Carmel/IU_WVT.t
qseispy/tests/data/2008_Mw_5.2_Carmel/IU_WVT.z
qseispy/tests/data/2008_Mw_5.2_Carmel/NM_BLO.r
qseispy/tests/data/2008_Mw_5.2_Carmel/NM_BLO.t
qseispy/tests/data/2008_Mw_5.2_Carmel/NM_BLO.z
qseispy/tests/data/2008_Mw_5.2_Carmel/NM_FVM.r
qseispy/tests/data/2008_Mw_5.2_Carmel/NM_FVM.t
qseispy/tests/data/2008_Mw_5.2_Carmel/NM_FVM.z
qseispy/tests/data/2008_Mw_5.2_Carmel/NM_PVMO.r
qseispy/tests/data/2008_Mw_5.2_Carmel/NM_PVMO.t
qseispy/tests/data/2008_Mw_5.2_Carmel/NM_PVMO.z
qseispy/tests/data/2008_Mw_5.2_Carmel/NM_SIUC.r
qseispy/tests/data/2008_Mw_5.2_Carmel/NM_SIUC.t
qseispy/tests/data/2008_Mw_5.2_Carmel/NM_SIUC.z
qseispy/tests/data/2008_Mw_5.2_Carmel/NM_SLM.r
qseispy/tests/data/2008_Mw_5.2_Carmel/NM_SLM.t
qseispy/tests/data/2008_Mw_5.2_Carmel/NM_SLM.z
qseispy/tests/data/2008_Mw_5.2_Carmel/v_model_us.txt
qseispy/tests/data/v_model/1066a.nd
qseispy/tests/data/v_model/1066b.nd
qseispy/tests/data/v_model/ak135f.nd
qseispy/tests/data/v_model/ak135f_no_mud.nd
qseispy/tests/data/v_model/prem.nd
qseispy-0.1.2.dist-info/LICENSE
qseispy-0.1.2.dist-info/METADATA
qseispy-0.1.2.dist-info/WHEEL
qseispy-0.1.2.dist-info/RECORD
